OneBitAdder.v
module OneBitAdder (
  // Inputs.
  input x,
  input y,
  input carry_in,

  // Outputs.
  output sum, output carry_out
);
    // Description of the logic goes here.
    wire x_not;
    wire y_not;
    wire carry_in_not;
    wire i1, i2, i3, i4, i5, i6, i7, i8, i9, i10;

    assign x_not = ~x;
    assign y_not = ~y;
    assign carry_in_not = ~carry_in;

    // Let's describe circuit for sum.
    assign i1 = x_not & y_not;
    assign i5 = carry_in & i1;

    assign i2 = x_not & y;
    assign i6 = carry_in_not & i2;

    //assign i3 = x_not & y;
    assign i3 = x & y_not;
    assign i7 = carry_in_not & i3;

    assign i4 = x & y;
    assign i8 = carry_in & i4;

    assign i9 = i5 | i6;
    assign i10 = i7 | i8;

    assign sum = i9 | i10;

    // Carry out description.
    assign carry_out = (x & carry_in) | (y & carry_in) | (x & y);

endmodule

OneBitAdder.vcd
$version Generated by VerilatedVcd $end
$date Sun Feb 13 18:12:25 2022 $end
$timescale 1ps $end

 $scope module TOP $end
  $var wire  1 % carry_in $end
  $var wire  1 ' carry_out $end
  $var wire  1 & sum $end
  $var wire  1 # x $end
  $var wire  1 $ y $end
  $scope module OneBitAdder $end
   $var wire  1 % carry_in $end
   $var wire  1 * carry_in_not $end
   $var wire  1 ' carry_out $end
   $var wire  1 + i1 $end
   $var wire  1 4 i10 $end
   $var wire  1 , i2 $end
   $var wire  1 - i3 $end
   $var wire  1 . i4 $end
   $var wire  1 / i5 $end
   $var wire  1 0 i6 $end
   $var wire  1 1 i7 $end
   $var wire  1 2 i8 $end
   $var wire  1 3 i9 $end
   $var wire  1 & sum $end
   $var wire  1 # x $end
   $var wire  1 ( x_not $end
   $var wire  1 $ y $end
   $var wire  1 ) y_not $end
  $upscope $end
 $upscope $end
$enddefinitions $end


#0
0#
1$
1%
0&
0'
1(
0)
0*
0+
1,
0-
0.
0/
00
01
02
03
04
#1
1#
0$
1'
0(
1)
0,
1-
#2
0%
1*
11
14
#3
1$
1%
1&
0'
0)
0*
0-
1.
01
12
#4
0#
0%
1'
1(
1*
1,
0.
10
02
13
04
#5
1#
0$
1%
0'
0(
1)
0*
0,
1-
00
03
#6
0#
1$
0%
0&
1'
1(
0)
1*
1,
0-
10
13
#7
0$
1%
1&
0'
1)
0*
1+
0,
1/
00
#8
1#
0%
0(
1*
0+
1-
0/
11
03
14
#9
0#
1(
1+
0-
01
04
#10
1%
0&
0*
1/
13
#11
1#
1&
0(
0+
1-
0/
03
#12
0#
1$
0&
1'
1(
0)
1,
0-
#13
0$
1)
1+
0,
1/
13
#14
0%
1&
0'
1*
0/
03
#15
1$
0&
0)
0+
1,
10
13
#16
1#
0$
1&
0(
1)
0,
1-
00
11
03
14
#17
0#
1(
1+
0-
01
04
#18
1#
1$
0&
0(
0)
0+
1.
#19
1%
1'
0*
12
14
#20
0$
1&
1)
1-
0.
02
04
#21
0#
1$
0&
1(
0)
1,
0-
#22
0$
0%
1)
1*
1+
0,
#23
1#
1%
0'
0(
0*
0+
1-
#24
0#
1'
1(
1+
0-
1/
13
#25
1#
1&
0'
0(
0+
1-
0/
03
#26
0&
1'
#27
#28
0#
1$
0%
1(
0)
1*
1,
0-
10
13
#29
0$
1%
1&
0'
1)
0*
1+
0,
1/
00
#30
1#
1$
0(
0)
0+
1.
0/
12
03
14
#31
1'
#32
0#
1(
1,
0.
02
04
#33
1#
0&
0(
0,
1.
12
14
#34
0#
0%
1&
1(
1*
1,
0.
10
02
13
04
#35
1#
0$
0'
0(
1)
0,
1-
00
11
03
14
#36
0#
1(
1+
0-
01
04
#37
1#
1$
0&
0(
0)
0+
1.
#38
0#
1%
1'
1(
0*
1,
0.
#39
0$
1)
1+
0,
1/
13
#40
1$
0%
1&
0'
0)
1*
0+
1,
0/
10
#41
1#
0$
0(
1)
0,
1-
00
11
03
14
#42
0#
1$
1%
1(
0)
0*
1,
0-
01
04
#43
1#
0$
0%
0&
1'
0(
1)
1*
0,
1-
11
14
#44
1&
0'
#45
1$
0)
0-
1.
01
04
#46
0$
0&
1'
1)
1-
0.
11
14
#47
0#
1$
1&
0'
1(
0)
1,
0-
10
01
13
04
#48
0$
1%
1)
0*
1+
0,
1/
00
#49
#50
1#
0(
0+
1-
0/
03
#51
0#
0&
1'
1(
1+
0-
1/
13
#52
0%
1&
0'
1*
0/
03
#53
1#
0&
0(
0+
1-
11
14
#54
0#
1$
1&
1(
0)
1,
0-
10
01
13
04
#55
0$
1)
1+
0,
00
03
#56
1$
0&
0)
0+
1,
10
13
#57
1#
1%
1&
0(
0*
0,
1.
00
12
03
14
#58
0$
1'
1)
1-
0.
02
04
#59
0#
0%
0&
1(
1*
1+
0-
#60
1$
0'
0)
0+
1,
10
13
#61
1#
1&
0(
0,
1.
00
03
#62
0#
1%
0&
1'
1(
0*
1,
0.
#63
1#
0(
0,
1.
12
14
#64
0%
1&
1*
02
04
#65
0#
0&
1(
1,
0.
10
13
#66
1%
1&
0'
0*
00
03
#67
0$
0&
1'
1)
1+
0,
1/
13
#68
1#
1$
1&
0'
0(
0)
0+
1.
0/
12
03
14
#69
0$
1'
1)
1-
0.
02
04
#70
0%
0&
1*
11
14
#71
1$
1&
0'
0)
0-
1.
01
04
#72
0#
1%
0&
1'
1(
0*
1,
0.
#73
1#
0$
0%
0(
1)
1*
0,
1-
11
14
#74
0#
1%
1&
0'
1(
0*
1+
0-
1/
01
13
04
#75
0%
1*
0/
03
#76
0&
#77
1#
0(
0+
1-
11
14
#78
0#
1$
1&
1(
0)
1,
0-
10
01
13
04
#79
1#
0$
0(
1)
0,
1-
00
11
03
14
#80
0#
1$
1(
0)
1,
0-
10
01
13
04
#81
1#
1%
0(
0*
0,
1.
00
12
03
14
#82
0%
1'
1*
02
04
#83
0#
0$
1%
0&
1(
1)
0*
1+
0.
1/
13
#84
1#
1&
0'
0(
0+
1-
0/
03
#85
0#
0&
1'
1(
1+
0-
1/
13
#86
1#
1&
0'
0(
0+
1-
0/
03
#87
1$
0&
1'
0)
0-
1.
12
14
#88
0$
0%
1&
1)
1*
1-
0.
11
02
#89
1$
1%
0'
0)
0*
0-
1.
01
12
#90
0$
0%
1'
1)
1*
1-
0.
11
02
#91
1$
1%
0'
0)
0*
0-
1.
01
12
#92
0#
0$
0%
1'
1(
1)
1*
1+
0.
02
04
#93
1#
0&
0'
0(
0+
1-
11
14
#94
0#
1$
1&
1(
0)
1,
0-
10
01
13
04
#95
1#
0$
0(
1)
0,
1-
00
11
03
14
#96
0#
1$
1(
0)
1,
0-
10
01
13
04
#97
1#
0$
0(
1)
0,
1-
00
11
03
14
#98
0#
1$
1(
0)
1,
0-
10
01
13
04
#99
1%
0*
00
03
#100
1#
0$
0&
1'
0(
1)
0,
1-
#101
0#
0%
1(
1*
1+
0-
#102
1#
0'
0(
0+
1-
11
14
#103
0#
1$
1%
1&
1(
0)
0*
1,
0-
01
04
#104
0%
0&
1'
1*
10
13
#105
1#
0$
1&
0'
0(
1)
0,
1-
00
11
03
14
#106
1%
0*
01
04
#107
0#
1$
0&
1'
1(
0)
1,
0-
#108
#109
0$
0%
1)
1*
1+
0,
#110
1#
1$
0'
0(
0)
0+
1.
#111
1'
#112
1%
0*
12
14
#113
0#
0%
1&
1(
1*
1,
0.
10
02
13
04
#114
1#
0'
0(
0,
1.
00
03
#115
0$
0&
1'
1)
1-
0.
11
14
#116
0#
1%
1&
0'
1(
0*
1+
0-
1/
01
13
04
#117
1#
0%
0(
1*
0+
1-
0/
11
03
14
#118
#119
0#
1(
1+
0-
01
04
#120
1$
1%
0&
0)
0*
0+
1,
#121
0$
1'
1)
1+
0,
1/
13
#122
1#
0%
1&
0'
0(
1*
0+
1-
0/
11
03
14
#123
0#
1%
1(
0*
1+
0-
1/
01
13
04
#124
1$
0%
0)
1*
0+
1,
0/
10
#125
0$
1%
1)
0*
1+
0,
1/
00
#126
1#
0(
0+
1-
0/
03
#127
0#
0&
1'
1(
1+
0-
1/
13
#128
1$
1&
0'
0)
0+
1,
0/
03
#129
0&
1'
#130
0%
1*
10
13
#131
1%
1&
0'
0*
00
03
#132
1#
0$
0&
1'
0(
1)
0,
1-
#133
#134
0#
1$
0%
1(
0)
1*
1,
0-
10
13
#135
1&
0'
#136
1#
0$
1%
0(
1)
0*
0,
1-
00
03
#137
0#
0&
1'
1(
1+
0-
1/
13
#138
1#
1$
0%
1&
0'
0(
0)
1*
0+
1.
0/
03
#139
0#
1%
0&
1'
1(
0*
1,
0.
#140
1#
0$
0%
0(
1)
1*
0,
1-
11
14
#141
0#
1%
1&
0'
1(
0*
1+
0-
1/
01
13
04
#142
1#
1$
0%
0(
0)
1*
0+
1.
0/
03
#143
0#
0$
0&
1'
1(
1)
1+
0.
#144
1#
1%
0'
0(
0*
0+
1-
#145
1'
#146
#147
0#
0%
1(
1*
1+
0-
#148
1#
1%
0'
0(
0*
0+
1-
#149
0%
1'
1*
11
14
#150
0#
1&
0'
1(
1+
0-
01
04
#151
0&
#152
1$
1%
0)
0*
0+
1,
#153
1'
#154
0$
1)
1+
0,
1/
13
#155
1$
0%
1&
0'
0)
1*
0+
1,
0/
10
#156
1#
0$
0(
1)
0,
1-
00
11
03
14
#157
0#
1$
1(
0)
1,
0-
10
01
13
04
#158
0$
1)
1+
0,
00
03
#159
1#
1%
0&
0(
0*
0+
1-
#160
0#
1'
1(
1+
0-
1/
13
#161
1$
1&
0'
0)
0+
1,
0/
03
#162
1#
0%
0&
1'
0(
1*
0,
1.
#163
0#
1%
1(
0*
1,
0.
#164
#165
1#
0%
0(
1*
0,
1.
#166
0$
1)
1-
0.
11
14
#167
1$
1%
1&
0'
0)
0*
0-
1.
01
12
#168
0#
0%
1'
1(
1*
1,
0.
10
02
13
04
#169
0'
#170
1#
0(
0,
1.
00
03
#171
0#
1%
0&
1'
1(
0*
1,
0.
#172
1#
0$
0%
0(
1)
1*
0,
1-
11
14
#173
1$
1%
1&
0'
0)
0*
0-
1.
01
12
#174
0#
1'
1(
1,
0.
02
04
#175
1#
0$
0%
0&
0(
1)
1*
0,
1-
11
14
#176
1%
1&
0'
0*
01
04
#177
0#
1$
0%
0&
1'
1(
0)
1*
1,
0-
10
13
#178
1#
1%
1&
0'
0(
0*
0,
1.
00
12
03
14
#179
0$
0%
1'
1)
1*
1-
0.
11
02
#180
1$
1%
0'
0)
0*
0-
1.
01
12
#181
0#
0$
1'
1(
1)
1+
0.
1/
02
13
04
#182
1#
1$
0'
0(
0)
0+
1.
0/
12
03
14
#183
0#
0%
1'
1(
1*
1,
0.
10
02
13
04
#184
1#
1%
0'
0(
0*
0,
1.
00
12
03
14
#185
0#
0%
1'
1(
1*
1,
0.
10
02
13
04
#186
1#
0$
0'
0(
1)
0,
1-
00
11
03
14
#187
0#
1%
1(
0*
1+
0-
1/
01
13
04
#188
#189
1#
1$
0(
0)
0+
1.
0/
12
03
14
#190
0#
0%
1'
1(
1*
1,
0.
10
02
13
04
#191
1#
0'
0(
0,
1.
00
03
#192
0#
0$
0&
1'
1(
1)
1+
0.
#193
1%
0'
0*
1/
13
#194
0%
1&
1*
0/
03
#195
1%
0&
0*
1/
13
#196
1$
0%
1&
0)
1*
0+
1,
0/
10
#197
#198
1#
0(
0,
1.
00
03
#199
0#
0&
1'
1(
1,
0.
10
13
#200
1#
1%
1&
0'
0(
0*
0,
1.
00
12
03
14
#201
0#
0$
0%
1'
1(
1)
1*
1+
0.
02
04
#202
1$
0&
0'
0)
0+
1,
10
13
#203
1%
1&
0*
00
03
#204
1#
0&
1'
0(
0,
1.
12
14
#205
0#
1&
1(
1,
0.
02
04
#206
1#
0&
0(
0,
1.
12
14
#207
0%
1&
1*
02
04
#208
0#
0&
1(
1,
0.
10
13
#209
1%
1&
0'
0*
00
03
#210
0%
0&
1'
1*
10
13
#211
1#
1&
0'
0(
0,
1.
00
03
#212
1%
0&
1'
0*
12
14
#213
0#
0$
0%
1&
1(
1)
1*
1+
0.
02
04
#214
1#
1$
0&
0'
0(
0)
0+
1.
#215
0#
1%
1'
1(
0*
1,
0.
#216
1#
0(
0,
1.
12
14
#217
0#
0$
0%
1&
1(
1)
1*
1+
0.
02
04
#218
1#
1%
0&
0'
0(
0*
0+
1-
#219
1$
1'
0)
0-
1.
12
14
#220
0#
0%
1&
1(
1*
1,
0.
10
02
13
04
#221
1%
0'
0*
00
03
#222
0$
0%
0&
1'
1)
1*
1+
0,
#223
0'
#224
1$
0)
0+
1,
10
13
#225
1%
1&
0*
00
03
#226
0%
0&
1'
1*
10
13
#227
1#
1%
1&
0'
0(
0*
0,
1.
00
12
03
14
#228
0$
1'
1)
1-
0.
02
04
#229
1$
0%
0&
0)
1*
0-
1.
#230
0#
1(
1,
0.
10
13
#231
1%
1&
0'
0*
00
03
#232
1#
0$
0&
1'
0(
1)
0,
1-
#233
0%
1*
11
14
#234
0#
1%
1&
0'
1(
0*
1+
0-
1/
01
13
04
#235
1$
0)
0+
1,
0/
03
#236
1#
0%
0&
1'
0(
1*
0,
1.
#237
0#
0$
1%
1(
1)
0*
1+
0.
1/
13
#238
1#
1$
0%
1&
0'
0(
0)
1*
0+
1.
0/
03
#239
0#
0$
1%
0&
1'
1(
1)
0*
1+
0.
1/
13
#240
1#
1&
0'
0(
0+
1-
0/
03
#241
0%
0&
1'
1*
11
14
#242
0#
1$
1&
0'
1(
0)
1,
0-
10
01
13
04
#243
1#
0(
0,
1.
00
03
#244
1%
0&
1'
0*
12
14
#245
0%
1&
1*
02
04
#246
0#
0$
1%
0&
1(
1)
0*
1+
0.
1/
13
#247
1&
0'
#248
1#
1$
0%
0(
0)
1*
0+
1.
0/
03
#249
0$
1%
0&
1'
1)
0*
1-
0.
#250
1$
0)
0-
1.
12
14
#251
0#
0$
0%
1&
1(
1)
1*
1+
0.
02
04
#252
1%
0&
0'
0*
1/
13
#253
1#
1$
0%
1&
0(
0)
1*
0+
1.
0/
03
#254
1%
0&
1'
0*
12
14
#255
0#
0$
0%
1&
1(
1)
1*
1+
0.
02
04
#256
1%
0&
0'
0*
1/
13
#257
1#
1&
0(
0+
1-
0/
03
#258
0#
1$
0&
1'
1(
0)
1,
0-
#259
1#
0(
0,
1.
12
14
#260
0#
0$
0%
1&
1(
1)
1*
1+
0.
02
04
#261
1#
0&
0'
0(
0+
1-
11
14
#262
1&
#263
1$
1%
0)
0*
0-
1.
01
12
#264
0%
1'
1*
02
04
#265
0&
#266
0$
1)
1-
0.
11
14
#267
0#
1$
1&
0'
1(
0)
1,
0-
10
01
13
04
#268
0$
1)
1+
0,
00
03
#269
1#
1$
1%
0&
0(
0)
0*
0+
1.
12
14
#270
0#
1&
1'
1(
1,
0.
02
04
#271
0$
0&
1)
1+
0,
1/
13
#272
1&
0'
#273
1$
0)
0+
1,
0/
03
#274
1#
0$
0%
0&
1'
0(
1)
1*
0,
1-
11
14
#275
0#
1$
1%
1&
0'
1(
0)
0*
1,
0-
01
04
#276
0&
1'
#277
1#
0(
0,
1.
12
14
#278
1&
#279
0$
0%
1)
1*
1-
0.
11
02
#280
0#
1%
0'
1(
0*
1+
0-
1/
01
13
04
#281
1#
0(
0+
1-
0/
03
#282
0#
0&
1'
1(
1+
0-
1/
13
#283
0%
1&
0'
1*
0/
03
#284
1#
1%
0&
0(
0*
0+
1-
#285
0%
1'
1*
11
14
#286
0#
1%
1&
0'
1(
0*
1+
0-
1/
01
13
04
#287
1$
0)
0+
1,
0/
03
#288
1#
0%
0&
1'
0(
1*
0,
1.
#289
0#
0$
1%
1(
1)
0*
1+
0.
1/
13
#290
1$
1&
0'
0)
0+
1,
0/
03
#291
1#
0$
0%
0&
1'
0(
1)
1*
0,
1-
11
14
#292
0#
1$
1&
0'
1(
0)
1,
0-
10
01
13
04
#293
1%
0*
00
03
#294
0$
0&
1'
1)
1+
0,
1/
13
#295
1#
1$
1&
0'
0(
0)
0+
1.
0/
12
03
14
#296
0#
1'
1(
1,
0.
02
04
#297
1#
0&
0(
0,
1.
12
14
#298
0#
0$
0%
1&
1(
1)
1*
1+
0.
02
04
#299
1#
0&
0'
0(
0+
1-
11
14
#300
0#
1%
1&
1(
0*
1+
0-
1/
01
13
04
#301
1#
1$
0%
0(
0)
1*
0+
1.
0/
03
#302
0$
1%
0&
1'
1)
0*
1-
0.
#303
0#
0%
1(
1*
1+
0-
#304
1#
0'
0(
0+
1-
11
14
#305
0#
1%
1&
1(
0*
1+
0-
1/
01
13
04
#306
1#
0%
0(
1*
0+
1-
0/
11
03
14
#307
0#
1$
1(
0)
1,
0-
10
01
13
04
#308
1#
0$
0(
1)
0,
1-
00
11
03
14
#309
1$
1%
0)
0*
0-
1.
01
12
#310
0#
1'
1(
1,
0.
02
04
#311
1#
0$
0&
0(
1)
0,
1-
#312
#313
0#
1(
1+
0-
1/
13
#314
1$
1&
0'
0)
0+
1,
0/
03
#315
0&
1'
#316
1#
0$
0(
1)
0,
1-
#317
0#
1(
1+
0-
1/
13
#318
1&
0'
#319
1$
0%
0)
1*
0+
1,
0/
10
#320
1#
1%
0(
0*
0,
1.
00
12
03
14
#321
1'
#322
0#
0$
1(
1)
1+
0.
1/
02
13
04
#323
1#
1$
0'
0(
0)
0+
1.
0/
12
03
14
#324
0#
0%
1'
1(
1*
1,
0.
10
02
13
04
#325
1#
0$
1%
0'
0(
1)
0*
0,
1-
00
03
#326
1$
0&
1'
0)
0-
1.
12
14
#327
0#
0%
1&
1(
1*
1,
0.
10
02
13
04
#328
1#
0'
0(
0,
1.
00
03
#329
0#
0$
1%
0&
1'
1(
1)
0*
1+
0.
1/
13
#330
1$
1&
0'
0)
0+
1,
0/
03
#331
1#
0$
0%
0&
1'
0(
1)
1*
0,
1-
11
14
#332
1&
0'
#333
0#
1$
1%
1(
0)
0*
1,
0-
01
04
#334
0&
1'
#335
#336
0$
0%
1)
1*
1+
0,
#337
1#
0'
0(
0+
1-
11
14
#338
1%
1&
0*
01
04
#339
0&
1'
#340
1$
0)
0-
1.
12
14
#341
0#
0$
1&
1(
1)
1+
0.
1/
02
13
04
#342
1$
0%
0'
0)
1*
0+
1,
0/
10
#343
0$
1%
1)
0*
1+
0,
1/
00
#344
#345
1#
0%
0(
1*
0+
1-
0/
11
03
14
#346
0#
1(
1+
0-
01
04
#347
0&
#348
1$
0)
0+
1,
10
13
#349
1%
1&
0*
00
03
#350
1#
0$
0%
0&
1'
0(
1)
1*
0,
1-
11
14
#351
0#
1&
0'
1(
1+
0-
01
04
#352
0&
#353
#354
1#
0(
0+
1-
11
14
#355
0#
1$
1&
1(
0)
1,
0-
10
01
13
04
#356
1%
0*
00
03
#357
0$
0&
1'
1)
1+
0,
1/
13
#358
1#
0%
1&
0'
0(
1*
0+
1-
0/
11
03
14
#359
1%
0*
01
04
#360
0#
0&
1'
1(
1+
0-
1/
13
#361
1&
0'
#362
1#
0(
0+
1-
0/
03
#363
0%
0&
1'
1*
11
14
#364
1&
0'
#365
#366
1$
1%
0)
0*
0-
1.
01
12
#367
0#
1'
1(
1,
0.
02
04
#368
1#
0$
0%
0&
0(
1)
1*
0,
1-
11
14
#369
0#
1&
0'
1(
1+
0-
01
04
#370
1#
0&
0(
0+
1-
11
14
#371
1$
1%
1&
0)
0*
0-
1.
01
12
#372
0#
0$
1'
1(
1)
1+
0.
1/
02
13
04
#373
1$
0%
0'
0)
1*
0+
1,
0/
10
#374
0$
1)
1+
0,
00
03
#375
1$
0&
0)
0+
1,
10
13
#376
0$
1%
1&
1)
0*
1+
0,
1/
00
#377
1$
0)
0+
1,
0/
03
#378
1#
0$
0&
1'
0(
1)
0,
1-
#379
#380
0#
0%
1(
1*
1+
0-
#381
1$
1%
0'
0)
0*
0+
1,
#382
1#
1'
0(
0,
1.
12
14
#383
0%
1&
1*
02
04
#384
0&
#385
0$
1%
1)
0*
1-
0.
#386
#387
0%
1*
11
14
#388
0#
1%
1&
0'
1(
0*
1+
0-
1/
01
13
04
#389
1#
1$
0(
0)
0+
1.
0/
12
03
14
#390
1'
#391
0$
0%
1)
1*
1-
0.
11
02
#392
0#
1$
0'
1(
0)
1,
0-
10
01
13
04
#393
1#
0$
1%
0(
1)
0*
0,
1-
00
03
#394
1$
0&
1'
0)
0-
1.
12
14
#395
0$
1&
1)
1-
0.
02
04
#396
0#
0&
1(
1+
0-
1/
13
#397
1#
1$
0%
1&
0'
0(
0)
1*
0+
1.
0/
03
#398
0#
0&
1'
1(
1,
0.
10
13
#399
1#
0$
1%
1&
0'
0(
1)
0*
0,
1-
00
03
#400
0#
1$
0&
1'
1(
0)
1,
0-
#401
0$
1)
1+
0,
1/
13
#402
0%
1&
0'
1*
0/
03
#403
1$
1%
0&
0)
0*
0+
1,
#404
0$
0%
1'
1)
1*
1+
0,
#405
1#
1$
1%
0'
0(
0)
0*
0+
1.
12
14
#406
0#
1&
1'
1(
1,
0.
02
04
#407
1#
0%
0&
0(
1*
0,
1.
#408
1%
0*
12
14
#409
0$
1&
1)
1-
0.
02
04
#410
0&
#411
0#
1(
1+
0-
1/
13
#412
1#
1$
0%
1&
0'
0(
0)
1*
0+
1.
0/
03
#413
1%
0&
1'
0*
12
14
#414
0#
0%
1&
1(
1*
1,
0.
10
02
13
04
#415
1#
0$
1%
0'
0(
1)
0*
0,
1-
00
03
#416
0#
0&
1'
1(
1+
0-
1/
13
#417
1#
0%
1&
0'
0(
1*
0+
1-
0/
11
03
14
#418
1$
1%
0)
0*
0-
1.
01
12
#419
0#
1'
1(
1,
0.
02
04
#420
1#
0$
0&
0(
1)
0,
1-
#421
0#
0%
1(
1*
1+
0-
#422
1$
1%
0'
0)
0*
0+
1,
#423
0$
0%
1'
1)
1*
1+
0,
#424
1#
1$
0'
0(
0)
0+
1.
#425
0$
1'
1)
1-
0.
11
14
#426
1%
1&
0'
0*
01
04
#427
0#
1$
0&
1'
1(
0)
1,
0-
#428
0$
0%
1)
1*
1+
0,
#429
1#
1%
0'
0(
0*
0+
1-
#430
0#
1$
1'
1(
0)
1,
0-
#431
1#
0$
0(
1)
0,
1-
#432
0%
1*
11
14
#433
0#
1%
1&
0'
1(
0*
1+
0-
1/
01
13
04
#434
1#
1$
0%
0(
0)
1*
0+
1.
0/
03
#435
0&
1'
#436
0$
1)
1-
0.
11
14
#437
0#
1%
1&
0'
1(
0*
1+
0-
1/
01
13
04
#438
1#
0(
0+
1-
0/
03
#439
0#
1$
0&
1'
1(
0)
1,
0-
#440
1#
0%
0(
1*
0,
1.
#441
0$
1)
1-
0.
11
14
#442
0#
1&
0'
1(
1+
0-
01
04
#443
1#
0&
0(
0+
1-
11
14
#444
0#
1$
1&
1(
0)
1,
0-
10
01
13
04
#445
0$
1%
1)
0*
1+
0,
1/
00
#446
#447
#448
1#
0(
0+
1-
0/
03
#449
0#
0%
0&
1'
1(
1*
1+
0-
#450
1#
1$
1%
0'
0(
0)
0*
0+
1.
12
14
#451
0$
1&
1'
1)
1-
0.
02
04
#452
0#
1$
0&
1(
0)
1,
0-
#453
0$
0%
1)
1*
1+
0,
#454
1#
1%
0'
0(
0*
0+
1-
#455
0%
1'
1*
11
14
#456
0#
1&
0'
1(
1+
0-
01
04
#457
1#
0&
0(
0+
1-
11
14
#458
0#
1$
1&
1(
0)
1,
0-
10
01
13
04
#459
1#
0(
0,
1.
00
03
#460
0$
0&
1'
1)
1-
0.
11
14
#461
0#
1$
1&
0'
1(
0)
1,
0-
10
01
13
04
#462
1#
1%
0(
0*
0,
1.
00
12
03
14
#463
0$
1'
1)
1-
0.
02
04
#464
1$
0&
0)
0-
1.
12
14
#465
0#
0$
1&
1(
1)
1+
0.
1/
02
13
04
#466
0'
#467
1$
0)
0+
1,
0/
03
#468
1#
0%
0&
1'
0(
1*
0,
1.
#469
0$
1%
1)
0*
1-
0.
#470
0#
1$
1(
0)
1,
0-
#471
#472
0$
0%
1)
1*
1+
0,
#473
1$
0'
0)
0+
1,
10
13
#474
1#
0$
1%
1&
0(
1)
0*
0,
1-
00
03
#475
1$
0&
1'
0)
0-
1.
12
14
#476
0#
1&
1(
1,
0.
02
04
#477
0$
0%
0&
1)
1*
1+
0,
#478
1#
1$
1%
0'
0(
0)
0*
0+
1.
12
14
#479
0#
0$
1&
1'
1(
1)
1+
0.
1/
02
13
04
#480
1#
0%
0'
0(
1*
0+
1-
0/
11
03
14
#481
1%
0*
01
04
#482
0#
1$
0%
0&
1'
1(
0)
1*
1,
0-
10
13
#483
1%
1&
0'
0*
00
03
#484
1#
0$
0%
0&
1'
0(
1)
1*
0,
1-
11
14
#485
0#
1$
1%
1&
0'
1(
0)
0*
1,
0-
01
04
#486
0$
0%
0&
1'
1)
1*
1+
0,
#487
1#
0'
0(
0+
1-
11
14
#488
0#
1$
1%
1&
1(
0)
0*
1,
0-
01
04
#489
1#
0%
0&
1'
0(
1*
0,
1.
#490
#491
0$
1%
1)
0*
1-
0.
#492
0%
1*
11
14
#493
1%
1&
0'
0*
01
04
#494
0#
1$
0&
1'
1(
0)
1,
0-
#495
0$
1)
1+
0,
1/
13
#496
1#
1&
0'
0(
0+
1-
0/
03
#497
0#
1$
0&
1'
1(
0)
1,
0-
#498
0%
1*
10
13
#499
1&
0'
#500
0$
1%
1)
0*
1+
0,
1/
00
#501
1$
0)
0+
1,
0/
03
#502
1#
0$
0&
1'
0(
1)
0,
1-
#503
1$
0)
0-
1.
12
14
#504
0#
0$
1&
1(
1)
1+
0.
1/
02
13
04
#505
0'
#506
1#
0(
0+
1-
0/
03
#507
0#
0%
0&
1'
1(
1*
1+
0-
#508
1#
0'
0(
0+
1-
11
14
#509
1%
1&
0*
01
04
#510
0&
1'
#511
0#
1$
0%
1(
0)
1*
1,
0-
10
13
#512
1#
0$
1%
1&
0'
0(
1)
0*
0,
1-
00
03
#513
0#
0%
0&
1'
1(
1*
1+
0-
#514
0'
#515
1#
1%
0(
0*
0+
1-
#516
0#
1$
1'
1(
0)
1,
0-
#517
1#
0(
0,
1.
12
14
#518
0$
1&
1)
1-
0.
02
04
#519
0%
0&
1*
11
14
#520
0#
1$
1&
0'
1(
0)
1,
0-
10
01
13
04
#521
1#
0$
1%
0(
1)
0*
0,
1-
00
03
#522
0#
1$
0%
0&
1'
1(
0)
1*
1,
0-
10
13
#523
1#
0$
1&
0'
0(
1)
0,
1-
00
11
03
14
#524
#525
0#
1$
1%
1(
0)
0*
1,
0-
01
04
#526
1#
0%
0&
1'
0(
1*
0,
1.
#527
0#
0$
1(
1)
1+
0.
#528
1#
1$
0'
0(
0)
0+
1.
#529
0#
1'
1(
1,
0.
10
13
#530
1&
0'
#531
1#
0(
0,
1.
00
03
#532
0#
1%
0&
1'
1(
0*
1,
0.
#533
0$
1)
1+
0,
1/
13
#534
1$
1&
0'
0)
0+
1,
0/
03
#535
1#
0%
0&
1'
0(
1*
0,
1.
#536
0#
0$
1%
1(
1)
0*
1+
0.
1/
13
#537
1&
0'
#538
1$
0)
0+
1,
0/
03
#539
1#
0$
0%
0&
1'
0(
1)
1*
0,
1-
11
14
#540
1%
1&
0'
0*
01
04
#541
1$
0%
0&
1'
0)
1*
0-
1.
#542
0$
1%
1)
0*
1-
0.
#543
#544
0#
1$
1(
0)
1,
0-
#545
0$
0%
1)
1*
1+
0,
#546
1%
0'
0*
1/
13
#547
1&
#548
1#
1$
0(
0)
0+
1.
0/
12
03
14
#549
0#
0$
1'
1(
1)
1+
0.
1/
02
13
04
#550
1$
0'
0)
0+
1,
0/
03
#551
0&
1'
#552
0$
1)
1+
0,
1/
13
#553
1$
1&
0'
0)
0+
1,
0/
03
#554
1#
0$
0%
0&
1'
0(
1)
1*
0,
1-
11
14
#555
0#
1&
0'
1(
1+
0-
01
04
#556
1#
0&
0(
0+
1-
11
14
#557
0#
1%
1&
1(
0*
1+
0-
1/
01
13
04
#558
1#
0%
0(
1*
0+
1-
0/
11
03
14
#559
0#
1(
1+
0-
01
04
#560
1#
1$
1%
0&
0(
0)
0*
0+
1.
12
14
#561
0%
1&
1'
1*
02
04
#562
0#
1%
0&
1(
0*
1,
0.
#563
1#
0%
0(
1*
0,
1.
#564
0#
1(
1,
0.
10
13
#565
1#
1&
0'
0(
0,
1.
00
03
#566
0$
1%
0&
1'
1)
0*
1-
0.
#567
0#
1(
1+
0-
1/
13
#568
1#
1&
0'
0(
0+
1-
0/
03
#569
0%
0&
1'
1*
11
14
#570
1%
1&
0'
0*
01
04
#571
0#
1$
0%
0&
1'
1(
0)
1*
1,
0-
10
13
#572
1#
1%
1&
0'
0(
0*
0,
1.
00
12
03
14
#573
0#
0$
1'
1(
1)
1+
0.
1/
02
13
04
#574
0%
0'
1*
0/
03
#575
1#
1$
1%
0&
0(
0)
0*
0+
1.
12
14
#576
0%
1&
1'
1*
02
04
#577
0#
0&
1(
1,
0.
10
13
#578
0$
1&
0'
1)
1+
0,
00
03
#579
1#
1$
1%
0&
0(
0)
0*
0+
1.
12
14
#580
0$
1&
1'
1)
1-
0.
02
04
#581
0#
0%
0&
1(
1*
1+
0-
#582
1$
1%
0'
0)
0*
0+
1,
#583
1'
#584
1#
0$
0(
1)
0,
1-
#585
1$
0)
0-
1.
12
14
#586
0#
0$
0%
1&
1(
1)
1*
1+
0.
02
04
#587
1$
1%
0&
0'
0)
0*
0+
1,
#588
1#
1'
0(
0,
1.
12
14
#589
0$
0%
1&
1)
1*
1-
0.
11
02
#590
0#
0'
1(
1+
0-
01
04
#591
1#
0&
0(
0+
1-
11
14
#592
1$
1&
0)
0-
1.
01
04
#593
0#
1%
0&
1'
1(
0*
1,
0.
#594
1#
0$
0(
1)
0,
1-
#595
1$
0%
0)
1*
0-
1.
#596
0#
1%
1(
0*
1,
0.
#597
0$
0%
1)
1*
1+
0,
#598
1#
1$
1%
0'
0(
0)
0*
0+
1.
12
14
#599
0#
0$
1&
1'
1(
1)
1+
0.
1/
02
13
04
